{
    "results": [
    {
        "id": "1",
        "name": "Dune",
        "price": "18"
    },
    {
        "id": "2",
        "name": "Ender's Game",
        "price": "400"
    },
    {
        "id": "3",
        "name": "Neuromancer",
        "price": "1000"
    },
    {
        "id": "4",
        "name": "The Time Machine",
        "price": "500"
    },
    {
        "id": "5",
        "name": "Fahrenheit",
        "price": "500"
    },
    {
        "id": "6",
        "name": "Fahrenheit",
        "price": "500"
    },
    {
        "id": "7",
        "name": "Fahrenheit",
        "price": "500"
    },
    {
        "id": "8",
        "name": "Fahrenheit",
        "price": "500"
    },
    {
        "id": "9",
        "name": "Fahrenheit",
        "price": "500"
    },
    {
        "id": "10",
        "name": "Fahrenheit",
        "price": "500"
    },
    {
        "id": "11",
        "name": "Fahrenheit",
        "price": "500"
    },
    {
        "id": "12",
        "name": "Fahrenheit",
        "price": "500"
    },
    {
        "id": "13",
        "name": "Fahrenheit",
        "price": "500"
    },
    {
        "id": "14",
        "name": "Fahrenheit",
        "price": "500"
    },
    {
        "id": "15",
        "name": "Fahrenheit",
        "price": "500"
    },
    {
        "id": "16",
        "name": "Fahrenheit",
        "price": "500"
    }]
}
